physfields/__init__.py
physfields/field.py
physfields/scalarfield.py
physfields/vectorfield.py
physfields/zernike.py
physics_fields-0.1.0.dist-info/METADATA
physics_fields-0.1.0.dist-info/WHEEL
physics_fields-0.1.0.dist-info/RECORD
